{"add-rss.md":"BU-yGrIP","config_basic.md":"BBu1yrKb","config_basic_add.md":"BlOpGWfY","config_basic_other.md":"D2d6mi3f","config_basic_page.md":"2aUgCsNz","config_basic_rename.md":"DNzyivTQ","config_basic_rss.md":"CvT40cBv","config_basic_trackers.md":"DL4H_9MF","config_download.md":"1kpmAAiY","config_login.md":"CsHJixl-","config_message.md":"CyMCkzSu","config_proxy.md":"D62hwTLI","deploy_deploy.md":"ClI7hJOH","deploy_docker.md":"BipRpm08","deploy_dsm.md":"D9vrLLxb","deploy_windows.md":"e_qBWEqq","dev.md":"Dpx1C7XB","docs.md":"jUjT_b3L","faq.md":"CqtzO3NQ","index.md":"B7V6pzY5","other.md":"BuMlZ7fB","start.md":"Bscf6qMc"}
